picklecryptor/__init__.py
picklecryptor/picklecryptor.py
picklecryptor/test_picklecryptor.py
picklecryptor-0.0.5.dist-info/LICENSE
picklecryptor-0.0.5.dist-info/METADATA
picklecryptor-0.0.5.dist-info/WHEEL
picklecryptor-0.0.5.dist-info/top_level.txt
picklecryptor-0.0.5.dist-info/RECORD
