Metadata-Version: 2.1
Name: picklecryptor
Version: 0.0.5
Summary: UNKNOWN
Home-page: http://github.com/csm10495/picklecryptor
Author: csm10495
Author-email: csm10495@gmail.com
License: MIT License
Platform: UNKNOWN
Classifier: Intended Audience :: Developers
Classifier: Natural Language :: English
Classifier: Operating System :: POSIX
Classifier: Operating System :: Microsoft :: Windows
Classifier: Programming Language :: Python
Classifier: Programming Language :: Python :: 3
Requires-Python: >=3,!=3.0.*,!=3.1.*,!=3.2.*,!=3.3.*,!=3.4.*,!=3.5.*,!=3.6.*
Requires-Dist: pytest
Requires-Dist: pycryptodome
